fullsubtractor/fullsubtractor.v
module fullsubtractor (input a, input b, input bin, output difference, output borrow);
assign difference = a^b^bin;
assign borrow = ~a&b|~(a^b)&bin;
endmodule

fullsubtractor/fullsubtractor_tb.v
`timescale 1ns/1ps
module fullsubtractor_tb;
reg a,b,bin;
wire difference,borrow;


fullsubtractor uut(.a(a),.b(b),.bin(bin),.difference(difference),.borrow(borrow));

initial begin
$dumpfile("output.vcd");
$dumpvars(0, fullsubtractor_tb);
$monitor("Time=%0t |a=%b b=%b bin=%b |difference=%b borrow=%b",$time,a,b,bin,difference,borrow);

a=0; b=0; bin=0; #10;
a=0; b=0; bin=1; #10;
a=0; b=1; bin=0; #10;
a=0; b=1; bin=1; #10;
a=1; b=0; bin=0; #10;
a=1; b=0; bin=1; #10;
a=1; b=1; bin=0; #10;
a=1; b=1; bin=1; #10;

$finish;

end
endmodule

fullsubtractor/output.vcd
$date
	Mon Sep 21 08:20:26 2026
$end
$version
	Icarus Verilog
$end
$timescale
	1ps
$end
$scope module fullsubtractor_tb $end
$var wire 1 ! borrow $end
$var wire 1 " difference $end
$var reg 1 # a $end
$var reg 1 $ b $end
$var reg 1 % bin $end
$scope module uut $end
$var wire 1 & a $end
$var wire 1 ' b $end
$var wire 1 ( bin $end
$var wire 1 ! borrow $end
$var wire 1 " difference $end
$upscope $end
$upscope $end
$enddefinitions $end
#0
$dumpvars
0(
0'
0&
0%
0$
0#
0"
0!
$end
#10000
1!
1"
1%
1(
#20000
0%
0(
1$
1'
#30000
0"
1%
1(
#40000
0!
1"
0%
0(
0$
0'
1#
1&
#50000
0"
1%
1(
#60000
0%
0(
1$
1'
#70000
1!
1"
1%
1(
