fulladder/fulladder.v
module fulladder(input a, input b, input cin, output sum, output cout);
assign sum = a^b^cin;
assign cout = a&b|a&cin|b&cin;
endmodule

fulladder/fulladder_tb.v
`timescale 1ns/1ps
module fulladder_tb;
reg a,b,cin;
wire sum,cout;


fulladder uut(.a(a),.b(b),.cin(cin),.sum(sum),.cout(cout));

initial begin
$dumpfile("output.vcd");
$dumpvars(0, fulladder_tb);
$monitor("Time=%0t |a=%h b=%h cin=%h |sum=%b cout=%b",a,b,cin,cout);

a=0; b=0; cin=0; #10;
a=0; b=0; cin=1; #10;
a=0; b=1; cin=0; #10;
a=0; b=1; cin=1; #10;
a=1; b=0; cin=0; #10;
a=1; b=0; cin=1; #10;
a=1; b=1; cin=0; #10;
a=1; b=1; cin=1; #10;

$finish;

end
endmodule

fulladder/output.vcd
$date
	Sat Sep 19 19:15:46 2026
$end
$version
	Icarus Verilog
$end
$timescale
	1ps
$end
$scope module fulladder_tb $end
$var wire 1 ! cout $end
$var wire 1 " sum $end
$var reg 1 # a $end
$var reg 1 $ b $end
$var reg 1 % cin $end
$scope module uut $end
$var wire 1 & a $end
$var wire 1 ' b $end
$var wire 1 ( cin $end
$var wire 1 ! cout $end
$var wire 1 " sum $end
$upscope $end
$upscope $end
$enddefinitions $end
#0
$dumpvars
0(
0'
0&
0%
0$
0#
0"
0!
$end
#10000
1"
1%
1(
#20000
0%
0(
1$
1'
#30000
1!
0"
1%
1(
#40000
0!
1"
0%
0(
0$
0'
1#
1&
#50000
1!
0"
1%
1(
#60000
0%
0(
1$
1'
#70000
1"
1%
1(
